{
  "protocol_version" : "0.0.6",
  "configuration" : {
    "version" : "(6.10.0.104) (2019-12/5d03a6fe116)",
    "tlc" : "normal",
    "sigsgev" : "altstack",
    "notifications" : "kqueue",
    "architecture" : "amd64",
    "disabled_features" : "none",
    "smallconfig" : "disabled",
    "bigarrays" : "disabled",
    "softdebug" : "enabled",
    "interpreter" : "enabled",
    "llvm_support" : "0",
    "suspend" : "hybrid"
  },
  "memory" : {
    "Resident Size" : "158674944",
    "Virtual Size" : "4732502016",
    "minor_gc_time" : "216000",
    "major_gc_time" : "0",
    "minor_gc_count" : "1",
    "major_gc_count" : "0",
    "major_gc_time_concurrent" : "0"
 },
  "threads" : [
 {
    "is_managed" : true,
    "offset_free_hash" : "0x1cfb5decbf",
    "offset_rich_hash" : "0x1cfb5df079",
    "crashed" : true,
    "native_thread_id" : "0x70000b757000",
    "thread_info_addr" : "0x7ff028068a00",
    "thread_name" : "Thread Pool Worker",
    "ctx" : {
      "IP" : "0x7fff71ad22c6",
      "SP" : "0x70000b7555a8",
      "BP" : "0x70000b7555e0"
  },
    "managed_frames" : [
  {
      "is_managed" : "false",
      "native_address" : "unregistered"
   }
,
  {
      "is_managed" : "true",
      "guid" : "55ADAE45-46CD-485B-A70E-2948332EBE8C",
      "token" : "0x00000",
      "native_offset" : "0x0",
      "filename" : "mscorlib.dll",
      "sizeofimage" : "0x474000",
      "timestamp" : "0xcdf122ed",
      "il_offset" : "0x0000c"
   }
,
  {
      "is_managed" : "true",
      "guid" : "55ADAE45-46CD-485B-A70E-2948332EBE8C",
      "token" : "0x6001f8c",
      "native_offset" : "0x0",
      "filename" : "mscorlib.dll",
      "sizeofimage" : "0x474000",
      "timestamp" : "0xcdf122ed",
      "il_offset" : "0x0001a"
   }
,
  {
      "is_managed" : "true",
      "guid" : "55ADAE45-46CD-485B-A70E-2948332EBE8C",
      "token" : "0x6001f32",
      "native_offset" : "0x0",
      "filename" : "mscorlib.dll",
      "sizeofimage" : "0x474000",
      "timestamp" : "0xcdf122ed",
      "il_offset" : "0x00028"
   }
,
  {
      "is_managed" : "true",
      "guid" : "55ADAE45-46CD-485B-A70E-2948332EBE8C",
      "token" : "0x6001f30",
      "native_offset" : "0x0",
      "filename" : "mscorlib.dll",
      "sizeofimage" : "0x474000",
      "timestamp" : "0xcdf122ed",
      "il_offset" : "0x00002"
   }
,
  {
      "is_managed" : "true",
      "guid" : "E5BBCD86-B476-47FC-970E-F00D99CDBAB3",
      "token" : "0x6000084",
      "native_offset" : "0x0",
      "filename" : "MonoDevelop.MSBuildBuilder.exe",
      "sizeofimage" : "0x18000",
      "timestamp" : "0xc077b0d4",
      "il_offset" : "0x000ae"
   }
,
  {
      "is_managed" : "true",
      "guid" : "E5BBCD86-B476-47FC-970E-F00D99CDBAB3",
      "token" : "0x6000083",
      "native_offset" : "0x0",
      "filename" : "MonoDevelop.MSBuildBuilder.exe",
      "sizeofimage" : "0x18000",
      "timestamp" : "0xc077b0d4",
      "il_offset" : "0x00001"
   }
,
  {
      "is_managed" : "true",
      "guid" : "E5BBCD86-B476-47FC-970E-F00D99CDBAB3",
      "token" : "0x600006a",
      "native_offset" : "0x0",
      "filename" : "MonoDevelop.MSBuildBuilder.exe",
      "sizeofimage" : "0x18000",
      "timestamp" : "0xc077b0d4",
      "il_offset" : "0x00048"
   }
,
  {
      "is_managed" : "true",
      "guid" : "E5BBCD86-B476-47FC-970E-F00D99CDBAB3",
      "token" : "0x60000a1",
      "native_offset" : "0x0",
      "filename" : "MonoDevelop.MSBuildBuilder.exe",
      "sizeofimage" : "0x18000",
      "timestamp" : "0xc077b0d4",
      "il_offset" : "0x00001"
   }
,
  {
      "is_managed" : "true",
      "guid" : "E5BBCD86-B476-47FC-970E-F00D99CDBAB3",
      "token" : "0x6000067",
      "native_offset" : "0x0",
      "filename" : "MonoDevelop.MSBuildBuilder.exe",
      "sizeofimage" : "0x18000",
      "timestamp" : "0xc077b0d4",
      "il_offset" : "0x00001"
   }
,
  {
      "is_managed" : "true",
      "guid" : "E5BBCD86-B476-47FC-970E-F00D99CDBAB3",
      "token" : "0x6000075",
      "native_offset" : "0x0",
      "filename" : "MonoDevelop.MSBuildBuilder.exe",
      "sizeofimage" : "0x18000",
      "timestamp" : "0xc077b0d4",
      "il_offset" : "0x00057"
   }
,
  {
      "is_managed" : "true",
      "guid" : "E5BBCD86-B476-47FC-970E-F00D99CDBAB3",
      "token" : "0x00000",
      "native_offset" : "0x0",
      "filename" : "MonoDevelop.MSBuildBuilder.exe",
      "sizeofimage" : "0x18000",
      "timestamp" : "0xc077b0d4",
      "il_offset" : "0x0002a"
   }
,
  {
      "is_managed" : "false",
      "native_address" : "unregistered"
   }
,
  {
      "is_managed" : "true",
      "guid" : "55ADAE45-46CD-485B-A70E-2948332EBE8C",
      "token" : "0x00000",
      "native_offset" : "0x0",
      "filename" : "mscorlib.dll",
      "sizeofimage" : "0x474000",
      "timestamp" : "0xcdf122ed",
      "il_offset" : "0x0000c"
   }
,
  {
      "is_managed" : "true",
      "guid" : "55ADAE45-46CD-485B-A70E-2948332EBE8C",
      "token" : "0x6004ced",
      "native_offset" : "0x0",
      "filename" : "mscorlib.dll",
      "sizeofimage" : "0x474000",
      "timestamp" : "0xcdf122ed",
      "il_offset" : "0x0006a"
   }
,
  {
      "is_managed" : "true",
      "guid" : "55ADAE45-46CD-485B-A70E-2948332EBE8C",
      "token" : "0x60048d1",
      "native_offset" : "0x0",
      "filename" : "mscorlib.dll",
      "sizeofimage" : "0x474000",
      "timestamp" : "0xcdf122ed",
      "il_offset" : "0x00000"
   }
,
  {
      "is_managed" : "true",
      "guid" : "E5BBCD86-B476-47FC-970E-F00D99CDBAB3",
      "token" : "0x6000039",
      "native_offset" : "0x0",
      "filename" : "MonoDevelop.MSBuildBuilder.exe",
      "sizeofimage" : "0x18000",
      "timestamp" : "0xc077b0d4",
      "il_offset" : "0x00019"
   }
,
  {
      "is_managed" : "true",
      "guid" : "E5BBCD86-B476-47FC-970E-F00D99CDBAB3",
      "token" : "0x6000169",
      "native_offset" : "0x0",
      "filename" : "MonoDevelop.MSBuildBuilder.exe",
      "sizeofimage" : "0x18000",
      "timestamp" : "0xc077b0d4",
      "il_offset" : "0x00029"
   }
,
  {
      "is_managed" : "true",
      "guid" : "E5BBCD86-B476-47FC-970E-F00D99CDBAB3",
      "token" : "0x6000184",
      "native_offset" : "0x0",
      "filename" : "MonoDevelop.MSBuildBuilder.exe",
      "sizeofimage" : "0x18000",
      "timestamp" : "0xc077b0d4",
      "il_offset" : "0x00001"
   }
,
  {
      "is_managed" : "true",
      "guid" : "55ADAE45-46CD-485B-A70E-2948332EBE8C",
      "token" : "0x6001ff3",
      "native_offset" : "0x0",
      "filename" : "mscorlib.dll",
      "sizeofimage" : "0x474000",
      "timestamp" : "0xcdf122ed",
      "il_offset" : "0x00007"
   }
,
  {
      "is_managed" : "true",
      "guid" : "55ADAE45-46CD-485B-A70E-2948332EBE8C",
      "token" : "0x6001ece",
      "native_offset" : "0x0",
      "filename" : "mscorlib.dll",
      "sizeofimage" : "0x474000",
      "timestamp" : "0xcdf122ed",
      "il_offset" : "0x00071"
   }
,
  {
      "is_managed" : "true",
      "guid" : "55ADAE45-46CD-485B-A70E-2948332EBE8C",
      "token" : "0x6001ecc",
      "native_offset" : "0x0",
      "filename" : "mscorlib.dll",
      "sizeofimage" : "0x474000",
      "timestamp" : "0xcdf122ed",
      "il_offset" : "0x00000"
   }
,
  {
      "is_managed" : "true",
      "guid" : "55ADAE45-46CD-485B-A70E-2948332EBE8C",
      "token" : "0x6001ff1",
      "native_offset" : "0x0",
      "filename" : "mscorlib.dll",
      "sizeofimage" : "0x474000",
      "timestamp" : "0xcdf122ed",
      "il_offset" : "0x00021"
   }
,
  {
      "is_managed" : "true",
      "guid" : "55ADAE45-46CD-485B-A70E-2948332EBE8C",
      "token" : "0x6001fd9",
      "native_offset" : "0x0",
      "filename" : "mscorlib.dll",
      "sizeofimage" : "0x474000",
      "timestamp" : "0xcdf122ed",
      "il_offset" : "0x00074"
   }
,
  {
      "is_managed" : "true",
      "guid" : "55ADAE45-46CD-485B-A70E-2948332EBE8C",
      "token" : "0x6001fee",
      "native_offset" : "0x0",
      "filename" : "mscorlib.dll",
      "sizeofimage" : "0x474000",
      "timestamp" : "0xcdf122ed",
      "il_offset" : "0x00000"
   }
,
  {
      "is_managed" : "true",
      "guid" : "55ADAE45-46CD-485B-A70E-2948332EBE8C",
      "token" : "0x00000",
      "native_offset" : "0x0",
      "filename" : "mscorlib.dll",
      "sizeofimage" : "0x474000",
      "timestamp" : "0xcdf122ed",
      "il_offset" : "0x0002a"
   }

  ],
  "unmanaged_frames" : [
 {
    "is_managed" : "false",
    "native_address" : "0x10de26346",
    "native_offset" : "0x00000"
  }
,
 {
    "is_managed" : "false",
    "native_address" : "0x10dfc0aa5",
    "native_offset" : "0x00000"
  }
,
 {
    "is_managed" : "false",
    "native_address" : "0x10dfc111a",
    "native_offset" : "0x00000"
  }
,
 {
    "is_managed" : "false",
    "native_address" : "0x10de92da7",
    "native_offset" : "0x00000"
  }
,
 {
    "is_managed" : "false",
    "native_address" : "0x10de2afb5",
    "native_offset" : "0x00000"
  }
,
 {
    "is_managed" : "false",
    "native_address" : "0x10de9209f",
    "native_offset" : "0x00000"
  }
,
 {
    "is_managed" : "false",
    "native_address" : "0x7fff71b82b5d",
    "native_offset" : "0x00000"
  }
,
 {
    "is_managed" : "false",
    "native_address" : "0x10e0ebcbc",
    "native_offset" : "0x00000"
  }
,
 {
    "is_managed" : "false",
    "native_address" : "0x7fff71a3c6a6",
    "native_offset" : "0x00000"
  }
,
 {
    "is_managed" : "false",
    "native_address" : "0x10e090397",
    "native_offset" : "0x00000"
  }
,
 {
    "is_managed" : "false",
    "native_address" : "0x10e07127f",
    "native_offset" : "0x00000"
  }
,
 {
    "is_managed" : "false",
    "native_address" : "0x10e09071e",
    "native_offset" : "0x00000"
  }
,
 {
    "is_managed" : "false",
    "native_address" : "0x10e09089f",
    "native_offset" : "0x00000"
  }
,
 {
    "is_managed" : "false",
    "native_address" : "0x10df2d059",
    "native_offset" : "0x00000"
  }
,
 {
    "is_managed" : "false",
    "native_address" : "0x10df2d5f2",
    "native_offset" : "0x00000"
  }
,
 {
    "is_managed" : "false",
    "native_address" : "0x10e07e6d1",
    "native_offset" : "0x00000"
  }
,
 {
    "is_managed" : "false",
    "native_address" : "0x10e07ea70",
    "native_offset" : "0x00000"
  }
,
 {
    "is_managed" : "false",
    "native_address" : "0x10df2f706",
    "native_offset" : "0x00000"
  }
,
 {
    "is_managed" : "false",
    "native_address" : "0x10df53ab4",
    "native_offset" : "0x00000"
  }
,
 {
    "is_managed" : "true",
    "guid" : "55ADAE45-46CD-485B-A70E-2948332EBE8C",
    "token" : "0x00000",
    "native_offset" : "0x0",
    "filename" : "mscorlib.dll",
    "sizeofimage" : "0x474000",
    "timestamp" : "0xcdf122ed",
    "il_offset" : "0x00000"
  }
,
 {
    "is_managed" : "true",
    "guid" : "55ADAE45-46CD-485B-A70E-2948332EBE8C",
    "token" : "0x6001f8c",
    "native_offset" : "0x0",
    "filename" : "mscorlib.dll",
    "sizeofimage" : "0x474000",
    "timestamp" : "0xcdf122ed",
    "il_offset" : "0x00000"
  }
,
 {
    "is_managed" : "true",
    "guid" : "E5BBCD86-B476-47FC-970E-F00D99CDBAB3",
    "token" : "0x6000083",
    "native_offset" : "0x0",
    "filename" : "MonoDevelop.MSBuildBuilder.exe",
    "sizeofimage" : "0x18000",
    "timestamp" : "0xc077b0d4",
    "il_offset" : "0x00000"
  }
,
 {
    "is_managed" : "true",
    "guid" : "E5BBCD86-B476-47FC-970E-F00D99CDBAB3",
    "token" : "0x600006a",
    "native_offset" : "0x0",
    "filename" : "MonoDevelop.MSBuildBuilder.exe",
    "sizeofimage" : "0x18000",
    "timestamp" : "0xc077b0d4",
    "il_offset" : "0x00000"
  }
,
 {
    "is_managed" : "true",
    "guid" : "E5BBCD86-B476-47FC-970E-F00D99CDBAB3",
    "token" : "0x60000a1",
    "native_offset" : "0x0",
    "filename" : "MonoDevelop.MSBuildBuilder.exe",
    "sizeofimage" : "0x18000",
    "timestamp" : "0xc077b0d4",
    "il_offset" : "0x00000"
  }
,
 {
    "is_managed" : "true",
    "guid" : "E5BBCD86-B476-47FC-970E-F00D99CDBAB3",
    "token" : "0x6000067",
    "native_offset" : "0x0",
    "filename" : "MonoDevelop.MSBuildBuilder.exe",
    "sizeofimage" : "0x18000",
    "timestamp" : "0xc077b0d4",
    "il_offset" : "0x00000"
  }
,
 {
    "is_managed" : "true",
    "guid" : "E5BBCD86-B476-47FC-970E-F00D99CDBAB3",
    "token" : "0x6000075",
    "native_offset" : "0x0",
    "filename" : "MonoDevelop.MSBuildBuilder.exe",
    "sizeofimage" : "0x18000",
    "timestamp" : "0xc077b0d4",
    "il_offset" : "0x00000"
  }
,
 {
    "is_managed" : "true",
    "guid" : "E5BBCD86-B476-47FC-970E-F00D99CDBAB3",
    "token" : "0x00000",
    "native_offset" : "0x0",
    "filename" : "MonoDevelop.MSBuildBuilder.exe",
    "sizeofimage" : "0x18000",
    "timestamp" : "0xc077b0d4",
    "il_offset" : "0x00000"
  }
,
 {
    "is_managed" : "false",
    "native_address" : "0x10dd88ae2",
    "native_offset" : "0x00000"
  }
,
 {
    "is_managed" : "false",
    "native_address" : "0x10df96967",
    "native_offset" : "0x00000"
  }
,
 {
    "is_managed" : "false",
    "native_address" : "0x10df9f409",
    "native_offset" : "0x00000"
  }
,
 {
    "is_managed" : "false",
    "native_address" : "0x10df3738d",
    "native_offset" : "0x00000"
  }
,
 {
    "is_managed" : "false",
    "native_address" : "0x10df4b027",
    "native_offset" : "0x00000"
  }
,
 {
    "is_managed" : "true",
    "guid" : "55ADAE45-46CD-485B-A70E-2948332EBE8C",
    "token" : "0x00000",
    "native_offset" : "0x0",
    "filename" : "mscorlib.dll",
    "sizeofimage" : "0x474000",
    "timestamp" : "0xcdf122ed",
    "il_offset" : "0x00000"
  }
,
 {
    "is_managed" : "true",
    "guid" : "55ADAE45-46CD-485B-A70E-2948332EBE8C",
    "token" : "0x6004ced",
    "native_offset" : "0x0",
    "filename" : "mscorlib.dll",
    "sizeofimage" : "0x474000",
    "timestamp" : "0xcdf122ed",
    "il_offset" : "0x00000"
  }
,
 {
    "is_managed" : "true",
    "guid" : "55ADAE45-46CD-485B-A70E-2948332EBE8C",
    "token" : "0x60048d1",
    "native_offset" : "0x0",
    "filename" : "mscorlib.dll",
    "sizeofimage" : "0x474000",
    "timestamp" : "0xcdf122ed",
    "il_offset" : "0x00000"
  }
,
 {
    "is_managed" : "true",
    "guid" : "E5BBCD86-B476-47FC-970E-F00D99CDBAB3",
    "token" : "0x6000169",
    "native_offset" : "0x0",
    "filename" : "MonoDevelop.MSBuildBuilder.exe",
    "sizeofimage" : "0x18000",
    "timestamp" : "0xc077b0d4",
    "il_offset" : "0x00000"
  }
,
 {
    "is_managed" : "true",
    "guid" : "E5BBCD86-B476-47FC-970E-F00D99CDBAB3",
    "token" : "0x6000184",
    "native_offset" : "0x0",
    "filename" : "MonoDevelop.MSBuildBuilder.exe",
    "sizeofimage" : "0x18000",
    "timestamp" : "0xc077b0d4",
    "il_offset" : "0x00000"
  }
,
 {
    "is_managed" : "true",
    "guid" : "55ADAE45-46CD-485B-A70E-2948332EBE8C",
    "token" : "0x6001ff3",
    "native_offset" : "0x0",
    "filename" : "mscorlib.dll",
    "sizeofimage" : "0x474000",
    "timestamp" : "0xcdf122ed",
    "il_offset" : "0x00000"
  }
,
 {
    "is_managed" : "true",
    "guid" : "55ADAE45-46CD-485B-A70E-2948332EBE8C",
    "token" : "0x6001ecc",
    "native_offset" : "0x0",
    "filename" : "mscorlib.dll",
    "sizeofimage" : "0x474000",
    "timestamp" : "0xcdf122ed",
    "il_offset" : "0x00000"
  }
,
 {
    "is_managed" : "true",
    "guid" : "55ADAE45-46CD-485B-A70E-2948332EBE8C",
    "token" : "0x6001fee",
    "native_offset" : "0x0",
    "filename" : "mscorlib.dll",
    "sizeofimage" : "0x474000",
    "timestamp" : "0xcdf122ed",
    "il_offset" : "0x00000"
  }
,
 {
    "is_managed" : "false",
    "native_address" : "0x10dd88ae2",
    "native_offset" : "0x00000"
  }
,
 {
    "is_managed" : "false",
    "native_address" : "0x10df98342",
    "native_offset" : "0x00000"
  }
,
 {
    "is_managed" : "false",
    "native_address" : "0x10dfc41c7",
    "native_offset" : "0x00000"
  }
,
 {
    "is_managed" : "false",
    "native_address" : "0x10def7f88",
    "native_offset" : "0x00000"
  }
,
 {
    "is_managed" : "false",
    "native_address" : "0x10dfc16ed",
    "native_offset" : "0x00000"
  }
,
 {
    "is_managed" : "false",
    "native_address" : "0x7fff71b8b2eb",
    "native_offset" : "0x00000"
  }
,
 {
    "is_managed" : "false",
    "native_address" : "0x7fff71b8e249",
    "native_offset" : "0x00000"
  }
,
 {
    "is_managed" : "false",
    "native_address" : "0x7fff71b8a40d",
    "native_offset" : "0x00000"
  }

 ]
},
{
  "is_managed" : false,
  "offset_free_hash" : "0x0",
  "offset_rich_hash" : "0x0",
  "crashed" : false,
  "native_thread_id" : "0x1127265c0",
  "thread_info_addr" : "0x7ff02700e400",
  "thread_name" : "tid_307",
  "ctx" : {
    "IP" : "0x7fff71acf86a",
    "SP" : "0x7ffee1e89c98",
    "BP" : "0x7ffee1e89d20"
 },
  "unmanaged_frames" : [
 {
    "is_managed" : "false",
    "native_address" : "0x10de26346",
    "native_offset" : "0x00000"
  }
,
 {
    "is_managed" : "false",
    "native_address" : "0x10dfc0aa5",
    "native_offset" : "0x00000"
  }
,
 {
    "is_managed" : "false",
    "native_address" : "0x10dfc07d7",
    "native_offset" : "0x00000"
  }
,
 {
    "is_managed" : "false",
    "native_address" : "0x10de91ce0",
    "native_offset" : "0x00000"
  }
,
 {
    "is_managed" : "false",
    "native_address" : "0x7fff71b82b5d",
    "native_offset" : "0x00000"
  }
,
 {
    "is_managed" : "false",
    "native_address" : "0x10de2897c",
    "native_offset" : "0x00000"
  }
,
 {
    "is_managed" : "false",
    "native_address" : "0x10e06d430",
    "native_offset" : "0x00000"
  }
,
 {
    "is_managed" : "false",
    "native_address" : "0x10e085401",
    "native_offset" : "0x00000"
  }
,
 {
    "is_managed" : "false",
    "native_address" : "0x10dfbd9e4",
    "native_offset" : "0x00000"
  }
,
 {
    "is_managed" : "false",
    "native_address" : "0x10dfbd7ea",
    "native_offset" : "0x00000"
  }
,
 {
    "is_managed" : "false",
    "native_address" : "0x10ddec30a",
    "native_offset" : "0x00000"
  }
,
 {
    "is_managed" : "false",
    "native_address" : "0x10dd77e49",
    "native_offset" : "0x00000"
  }
,
 {
    "is_managed" : "false",
    "native_address" : "0x7fff719973d5",
    "native_offset" : "0x00000"
  }

 ]
},
{
  "is_managed" : false,
  "offset_free_hash" : "0xb38e38cc",
  "offset_rich_hash" : "0xb38e38cc",
  "crashed" : false,
  "native_thread_id" : "0x70000ae45000",
  "thread_info_addr" : "0x7ff027828a00",
  "thread_name" : "Finalizer",
  "ctx" : {
    "IP" : "0x7fff71acc266",
    "SP" : "0x70000ae44e18",
    "BP" : "0x70000ae44e60"
 },
  "unmanaged_frames" : [
 {
    "is_managed" : "false",
    "native_address" : "0x10de26346",
    "native_offset" : "0x00000"
  }
,
 {
    "is_managed" : "false",
    "native_address" : "0x10dfc0aa5",
    "native_offset" : "0x00000"
  }
,
 {
    "is_managed" : "false",
    "native_address" : "0x10dfc07d7",
    "native_offset" : "0x00000"
  }
,
 {
    "is_managed" : "false",
    "native_address" : "0x10de91ce0",
    "native_offset" : "0x00000"
  }
,
 {
    "is_managed" : "false",
    "native_address" : "0x7fff71b82b5d",
    "native_offset" : "0x00000"
  }
,
 {
    "is_managed" : "true",
    "guid" : "55ADAE45-46CD-485B-A70E-2948332EBE8C",
    "token" : "0x6001467",
    "native_offset" : "0x0",
    "filename" : "mscorlib.dll",
    "sizeofimage" : "0x474000",
    "timestamp" : "0xcdf122ed",
    "il_offset" : "0x00000"
  }
,
 {
    "is_managed" : "false",
    "native_address" : "0x10dfc16ed",
    "native_offset" : "0x00000"
  }
,
 {
    "is_managed" : "false",
    "native_address" : "0x7fff71b8b2eb",
    "native_offset" : "0x00000"
  }
,
 {
    "is_managed" : "false",
    "native_address" : "0x7fff71b8e249",
    "native_offset" : "0x00000"
  }
,
 {
    "is_managed" : "false",
    "native_address" : "0x7fff71b8a40d",
    "native_offset" : "0x00000"
  }

 ]
}
]
}